mucos/__init__.py
mucos/mucos.py
mucos-0.2.dist-info/METADATA
mucos-0.2.dist-info/WHEEL
mucos-0.2.dist-info/licenses/LICENSE
mucos-0.2.dist-info/RECORD
